alpha_hybird_model/__init__.py
alpha_hybird_model/model.py
alpha_hybird_model/utils.py
scripts/__init__.py
scripts/train_model.py
alpha_hybird_model-0.1.1.dist-info/LICENSE
alpha_hybird_model-0.1.1.dist-info/METADATA
alpha_hybird_model-0.1.1.dist-info/WHEEL
alpha_hybird_model-0.1.1.dist-info/entry_points.txt
alpha_hybird_model-0.1.1.dist-info/top_level.txt
alpha_hybird_model-0.1.1.dist-info/RECORD
